reqtrace/__init__.py
reqtrace/__main__.py
reqtrace/langhelpers.py
reqtrace/messages.py
reqtrace/testing.py
reqtrace/util.py
reqtrace/commands/__init__.py
reqtrace/commands/echo.py
reqtrace/commands/reqtrace.py
reqtrace/mockserve/__init__.py
reqtrace/mockserve/core.py
reqtrace/mockserve/echohandler.py
reqtrace/mockserve/mirrorhandler.py
reqtrace/tracelib/__init__.py
reqtrace/tracelib/googleapi.py
reqtrace/tracelib/hooks.py
reqtrace/tracelib/httplib2.py
reqtrace/tracelib/models.py
reqtrace/tracelib/requests.py
reqtrace-0.0.1.dist-info/METADATA
reqtrace-0.0.1.dist-info/WHEEL
reqtrace-0.0.1.dist-info/entry_points.txt
reqtrace-0.0.1.dist-info/top_level.txt
reqtrace-0.0.1.dist-info/RECORD
